sqlite_ast/__init__.py
sqlite_ast/ast_nodes.py
sqlite_ast/parser.py
sqlite_ast/tokenizer.py
sqlite_ast-0.1a0.dist-info/licenses/LICENSE
sqlite_ast-0.1a0.dist-info/METADATA
sqlite_ast-0.1a0.dist-info/WHEEL
sqlite_ast-0.1a0.dist-info/top_level.txt
sqlite_ast-0.1a0.dist-info/RECORD
