Metadata-Version: 2.4
Name: sqlite-ast
Version: 0.1a0
Summary: Python library for parsing SQLite SELECT queries into an AST
Author: Simon Willison
License-Expression: Apache-2.0
Project-URL: Homepage, https://github.com/simonw/sqlite-ast
Project-URL: Changelog, https://github.com/simonw/sqlite-ast/releases
Project-URL: Issues, https://github.com/simonw/sqlite-ast/issues
Project-URL: CI, https://github.com/simonw/sqlite-ast/actions
Requires-Python: >=3.10
License-File: LICENSE
Dynamic: license-file
